juju_wait/__init__.py
juju_wait-2.8.4.dist-info/LICENSE.txt
juju_wait-2.8.4.dist-info/METADATA
juju_wait-2.8.4.dist-info/WHEEL
juju_wait-2.8.4.dist-info/entry_points.txt
juju_wait-2.8.4.dist-info/top_level.txt
juju_wait-2.8.4.dist-info/RECORD
