Metadata-Version: 2.1
Name: juju-wait
Version: 2.8.4
Summary: Juju plugin to wait for environment steady state
Home-page: https://launchpad.net/juju-wait
Author: Stuart Bishop
Author-email: stuart.bishop@canonical.com
License: GPLv3
Keywords: juju
Platform: UNKNOWN
Classifier: Development Status :: 5 - Production/Stable
Classifier: Environment :: Plugins
Classifier: Intended Audience :: Developers
Classifier: Intended Audience :: System Administrators
Classifier: License :: OSI Approved :: GNU General Public License v3 (GPLv3)
Classifier: Operating System :: OS Independent
Classifier: Topic :: System :: Installation/Setup
Classifier: Topic :: Utilities
Classifier: Programming Language :: Python :: 3
Requires-Dist: PyYAML
